pydcov/__init__.py
pydcov/cli.py
pydcov/cmake/__init__.py
pydcov/cmake/coverage.cmake
pydcov/core/__init__.py
pydcov/core/incremental_coverage.py
pydcov/utils/__init__.py
pydcov/utils/cmake_integration.py
pydcov/utils/compiler_detection.py
pydcov/utils/config.py
pydcov/utils/coverage_file_manager.py
pydcov/utils/coverage_tools.py
pydcov/utils/logging_config.py
pydcov/utils/path_utils.py
pydcov/utils/test_executor.py
pydcov-1.0.6.dist-info/licenses/LICENSE
pydcov-1.0.6.dist-info/METADATA
pydcov-1.0.6.dist-info/WHEEL
pydcov-1.0.6.dist-info/entry_points.txt
pydcov-1.0.6.dist-info/top_level.txt
pydcov-1.0.6.dist-info/RECORD
