Metadata-Version: 2.4
Name: pydcov
Version: 1.0.6
Summary: Incremental C/C++ code coverage tools for CMake projects
Author: Ethan Li
Maintainer: Ethan Li
License-Expression: MIT
Project-URL: Homepage, https://github.com/ethan-li/pydcov
Project-URL: Documentation, https://github.com/ethan-li/pydcov/blob/main/README.md
Project-URL: Repository, https://github.com/ethan-li/pydcov.git
Project-URL: Bug Tracker, https://github.com/ethan-li/pydcov/issues
Keywords: coverage,incremental,c,cpp,cmake,testing,gcov,llvm-cov
Classifier: Development Status :: 4 - Beta
Classifier: Intended Audience :: Developers
Classifier: Operating System :: OS Independent
Classifier: Programming Language :: Python :: 3
Classifier: Programming Language :: Python :: 3.11
Classifier: Programming Language :: Python :: 3.12
Classifier: Programming Language :: Python :: 3.13
Classifier: Programming Language :: C
Classifier: Programming Language :: C++
Classifier: Topic :: Software Development :: Testing
Classifier: Topic :: Software Development :: Quality Assurance
Requires-Python: >=3.11
License-File: LICENSE
Provides-Extra: dev
Requires-Dist: black>=22.0.0; extra == "dev"
Requires-Dist: flake8>=4.0.0; extra == "dev"
Requires-Dist: mypy>=0.900; extra == "dev"
Requires-Dist: pytest>=6.0.0; extra == "dev"
Requires-Dist: pyinstaller>=6.0.0; extra == "dev"
Dynamic: license-file
